recsys/feature/__init__.py
recsys/feature/utils.py
recsys/layers/activation.py
recsys/layers/aggregation.py
recsys/layers/core.py
recsys/layers/embedding.py
recsys/layers/interaction.py
recsys/layers/transformer.py
recsys/layers/utils.py
recsys/multidomain/m2m.py
recsys/multidomain/pepnet.py
recsys/multidomain/star.py
recsys/multitask/mmoe.py
recsys/multitask/ple.py
recsys/multitask/stem.py
recsys/rank/adaf2m2.py
recsys/rank/dcn.py
recsys/rank/deepfm.py
recsys/rank/din.py
recsys/rank/fibinet.py
recsys/rank/gwpfm.py
recsys/rank/hmoe.py
recsys/rank/pnn.py
recsys/rank/tin.py
recsys/train/losses.py
recsys/train/multi_opt_model.py
deep_rec_kit-1.0.2.dist-info/METADATA
deep_rec_kit-1.0.2.dist-info/WHEEL
deep_rec_kit-1.0.2.dist-info/licenses/LICENSE
deep_rec_kit-1.0.2.dist-info/RECORD
