Metadata-Version: 2.4
Name: deep-rec-kit
Version: 1.0.2
Summary: Recommendation system, including rank&match models and metrics, all implemented by `tensorflow & keras 2.x`
Project-URL: Homepage, https://github.com/QunBB/RecSys
Project-URL: Repository, https://github.com/QunBB/RecSys
Project-URL: Issues, https://github.com/QunBB/RecSys/issues
License-Expression: Apache-2.0
License-File: LICENSE
Classifier: Intended Audience :: Developers
Classifier: Operating System :: MacOS
Classifier: Operating System :: Microsoft :: Windows
Classifier: Operating System :: OS Independent
Classifier: Operating System :: POSIX
Classifier: Operating System :: POSIX :: Linux
Classifier: Programming Language :: Python :: 3.6
Classifier: Programming Language :: Python :: 3.7
Classifier: Programming Language :: Python :: 3.8
Classifier: Programming Language :: Python :: 3.9
Classifier: Programming Language :: Python :: 3.10
Classifier: Programming Language :: Python :: 3.11
Classifier: Topic :: Scientific/Engineering :: Artificial Intelligence
Classifier: Topic :: Software Development :: Libraries :: Python Modules
Classifier: Typing :: Typed
Requires-Python: <12,>=3.6
Requires-Dist: dataclasses
Requires-Dist: tensorflow<2.16,>=2
